rsa_key_info/__init__.py
rsa_key_info/main.py
rsa_key_info-24.2.24.2.dist-info/LICENSE
rsa_key_info-24.2.24.2.dist-info/METADATA
rsa_key_info-24.2.24.2.dist-info/WHEEL
rsa_key_info-24.2.24.2.dist-info/entry_points.txt
rsa_key_info-24.2.24.2.dist-info/top_level.txt
rsa_key_info-24.2.24.2.dist-info/RECORD
