Metadata-Version: 2.1
Name: rsa-key-info
Version: 24.2.24.2
Summary: Extracts information from a given public RSA key file.
Home-page: https://github.com/efcylab/rsa_key_info
Author: EfcyLab
Author-email: efcyla@proton.me
License-File: LICENSE
Requires-Dist: pycryptodome
Requires-Dist: pyfiglet
